MANIFEST.in
README.rst
setup.py
docs/HISTORY.txt
docs/LICENSE.GPL
docs/LICENSE.txt
ftw/__init__.py
ftw.treeview.egg-info/PKG-INFO
ftw.treeview.egg-info/SOURCES.txt
ftw.treeview.egg-info/dependency_links.txt
ftw.treeview.egg-info/entry_points.txt
ftw.treeview.egg-info/namespace_packages.txt
ftw.treeview.egg-info/not-zip-safe
ftw.treeview.egg-info/requires.txt
ftw.treeview.egg-info/top_level.txt
ftw/treeview/__init__.py
ftw/treeview/configure.zcml
ftw/treeview/navtree.py
ftw/treeview/recurse.pt
ftw/treeview/testing.py
ftw/treeview/view.py
ftw/treeview/Extensions/install.py
ftw/treeview/profiles/default/cssregistry.xml
ftw/treeview/profiles/default/jsregistry.xml
ftw/treeview/profiles/default/metadata.xml
ftw/treeview/profiles/default/skins.xml
ftw/treeview/profiles/uninstall/cssregistry.xml
ftw/treeview/profiles/uninstall/jsregistry.xml
ftw/treeview/profiles/uninstall/skins.xml
ftw/treeview/skins/ftw_treeview/file.gif
ftw/treeview/skins/ftw_treeview/folder-closed.gif
ftw/treeview/skins/ftw_treeview/folder.gif
ftw/treeview/skins/ftw_treeview/jquery.treeview.css
ftw/treeview/skins/ftw_treeview/jquery.treeview.js
ftw/treeview/skins/ftw_treeview/minus.gif
ftw/treeview/skins/ftw_treeview/plus.gif
ftw/treeview/skins/ftw_treeview/treeview-black-line.gif
ftw/treeview/skins/ftw_treeview/treeview-black.gif
ftw/treeview/skins/ftw_treeview/treeview-default-line.gif
ftw/treeview/skins/ftw_treeview/treeview-default.gif
ftw/treeview/skins/ftw_treeview/treeview-famfamfam-line.gif
ftw/treeview/skins/ftw_treeview/treeview-famfamfam.gif
ftw/treeview/skins/ftw_treeview/treeview-gray-line.gif
ftw/treeview/skins/ftw_treeview/treeview-gray.gif
ftw/treeview/skins/ftw_treeview/treeview-red-line.gif
ftw/treeview/skins/ftw_treeview/treeview-red.gif
ftw/treeview/tests/__init__.py
ftw/treeview/tests/test_uninstall.py