Metadata-Version: 1.1
Name: ftw.treeview
Version: 1.2.0
Summary: Adds a navigation treeview widget to plone.
Home-page: https://github.com/4teamwork/ftw.treeview
Author: 4teamwork AG
Author-email: mailto:info@4teamwork.ch
License: GPL
Platform: UNKNOWN
Classifier: Framework :: Plone
Classifier: Framework :: Plone :: 4.0
Classifier: Framework :: Plone :: 4.1
Classifier: Framework :: Plone :: 4.2
Classifier: Framework :: Plone :: 4.3
Classifier: Intended Audience :: Developers
Classifier: Programming Language :: Python
Classifier: Topic :: Software Development :: Libraries :: Python Modules
